{
  "@context" : {
    "WorkflowInstance" : {
      "@id" : "http://purl.org/wf4ever/wfdesc#WorkflowInstance"
    },
    "hasSubWorkflow" : {
      "@id" : "http://purl.org/wf4ever/wfdesc#hasSubWorkflow",
      "@type" : "@id"
    },
    "DataLink" : {
      "@id" : "http://purl.org/wf4ever/wfdesc#DataLink"
    },
    "hasSink" : {
      "@id" : "http://purl.org/wf4ever/wfdesc#hasSink",
      "@type" : "@id"
    },
    "hasSubProcess" : {
      "@id" : "http://purl.org/wf4ever/wfdesc#hasSubProcess",
      "@type" : "@id"
    },
    "hasInput" : {
      "@id" : "http://purl.org/wf4ever/wfdesc#hasInput",
      "@type" : "@id"
    },
    "hasOutput" : {
      "@id" : "http://purl.org/wf4ever/wfdesc#hasOutput",
      "@type" : "@id"
    },
    "hasSource" : {
      "@id" : "http://purl.org/wf4ever/wfdesc#hasSource",
      "@type" : "@id"
    },
    "Artifact" : {
      "@id" : "http://purl.org/wf4ever/wfdesc#Artifact"
    },
    "Output" : {
      "@id" : "http://purl.org/wf4ever/wfdesc#Output"
    },
    "Input" : {
      "@id" : "http://purl.org/wf4ever/wfdesc#Input"
    },
    "label" : {
      "@id" : "http://www.w3.org/2000/01/rdf-schema#label"
    },
    "comment" : {
      "@id" : "http://www.w3.org/2000/01/rdf-schema#comment"
    },
    "Parameter" : {
      "@id" : "http://purl.org/wf4ever/wfdesc#Parameter"
    },
    "hasArtifact" : {
      "@id" : "http://purl.org/wf4ever/wfdesc#hasArtifact",
      "@type" : "@id"
    },
    "Process" : {
      "@id" : "http://purl.org/wf4ever/wfdesc#Process"
    },
    "hasDataLink" : {
      "@id" : "http://purl.org/wf4ever/wfdesc#hasDataLink",
      "@type" : "@id"
    },
    "Workflow" : {
      "@id" : "http://purl.org/wf4ever/wfdesc#Workflow"
    }
  }
}
